github_release_counter/__init__.py
github_release_counter/cli.py
github_release_counter/display.py
github_release_counter/github_api.py
github_release_counter-2.0.0.dist-info/licenses/LICENSE
github_release_counter-2.0.0.dist-info/METADATA
github_release_counter-2.0.0.dist-info/WHEEL
github_release_counter-2.0.0.dist-info/entry_points.txt
github_release_counter-2.0.0.dist-info/top_level.txt
github_release_counter-2.0.0.dist-info/RECORD
