Metadata-Version: 2.4
Name: github-release-counter
Version: 2.0.0
Summary: A Python tool to count GitHub release downloads.
Author-email: Marco ML <marcoleija@marco-ml.com>
Project-URL: Homepage, https://github.com/marcomolinaleija/github-release-counter
Classifier: Programming Language :: Python :: 3
Classifier: License :: OSI Approved :: MIT License
Classifier: Operating System :: OS Independent
Requires-Python: >=3.7
License-File: LICENSE
Requires-Dist: requests
Dynamic: license-file
